MANIFEST.in
pyproject.toml
setup.py
version.txt
src/fiftyone_devicedetection_onpremise/DeviceDetectionHashEngineModule.py
src/fiftyone_devicedetection_onpremise/__init__.py
src/fiftyone_devicedetection_onpremise/constants.py
src/fiftyone_devicedetection_onpremise/devicedetection_datafile.py
src/fiftyone_devicedetection_onpremise/devicedetection_onpremise.py
src/fiftyone_devicedetection_onpremise/devicedetection_onpremise_pipelinebuilder.py
src/fiftyone_devicedetection_onpremise/hash_python_wrap.cxx
src/fiftyone_devicedetection_onpremise/swig_data.py
src/fiftyone_devicedetection_onpremise.egg-info/PKG-INFO
src/fiftyone_devicedetection_onpremise.egg-info/SOURCES.txt
src/fiftyone_devicedetection_onpremise.egg-info/dependency_links.txt
src/fiftyone_devicedetection_onpremise.egg-info/requires.txt
src/fiftyone_devicedetection_onpremise.egg-info/top_level.txt
src/fiftyone_devicedetection_onpremise/cxx/src/ConfigDeviceDetection.cpp
src/fiftyone_devicedetection_onpremise/cxx/src/ConfigDeviceDetection.hpp
src/fiftyone_devicedetection_onpremise/cxx/src/ConfigDeviceDetection.i
src/fiftyone_devicedetection_onpremise/cxx/src/EngineDeviceDetection.cpp
src/fiftyone_devicedetection_onpremise/cxx/src/EngineDeviceDetection.hpp
src/fiftyone_devicedetection_onpremise/cxx/src/EngineDeviceDetection.i
src/fiftyone_devicedetection_onpremise/cxx/src/EvidenceDeviceDetection.cpp
src/fiftyone_devicedetection_onpremise/cxx/src/EvidenceDeviceDetection.hpp
src/fiftyone_devicedetection_onpremise/cxx/src/EvidenceDeviceDetection.i
src/fiftyone_devicedetection_onpremise/cxx/src/FiftyoneDegrees.hpp
src/fiftyone_devicedetection_onpremise/cxx/src/ResultsDeviceDetection.cpp
src/fiftyone_devicedetection_onpremise/cxx/src/ResultsDeviceDetection.hpp
src/fiftyone_devicedetection_onpremise/cxx/src/ResultsDeviceDetection.i
src/fiftyone_devicedetection_onpremise/cxx/src/Transform.cpp
src/fiftyone_devicedetection_onpremise/cxx/src/Transform.hpp
src/fiftyone_devicedetection_onpremise/cxx/src/Transform.i
src/fiftyone_devicedetection_onpremise/cxx/src/config-dd.h
src/fiftyone_devicedetection_onpremise/cxx/src/dataset-dd.c
src/fiftyone_devicedetection_onpremise/cxx/src/dataset-dd.h
src/fiftyone_devicedetection_onpremise/cxx/src/fiftyone.h
src/fiftyone_devicedetection_onpremise/cxx/src/gethighentropyvalues.c
