Metadata-Version: 2.1
Name: fiftyone-devicedetection-onpremise
Version: 4.5.9
Summary: This project contains 51Degrees Device Detection OnPremise engine that can be used with the 51Degrees Pipeline API. The Pipeline is a generic web request intelligence and data processing solution with the ability to add a range of 51Degrees and/or custom plug ins (Engines)
Author: 51Degrees Engineering
Author-email: engineering@51degrees.com
License: EUPL-1.2
Requires-Python: >=3.8
